loggerbot/__init__.py
loggerbot/loggerbot.py
loggerbot/telegram_logging_bot.py
loggerbot-3.8.8.dist-info/LICENSE
loggerbot-3.8.8.dist-info/METADATA
loggerbot-3.8.8.dist-info/WHEEL
loggerbot-3.8.8.dist-info/top_level.txt
loggerbot-3.8.8.dist-info/RECORD
