Metadata-Version: 2.1
Name: loggerbot
Version: 3.8.8
Summary: A Telegram logging library with rate limiting and message queuing
Home-page: https://ubix.pro/
Author: N.Sikharulidze
Author-email: "N.Sikharulidze" <info@ubix.pro>
License: MIT License
Project-URL: Homepage, https://ubix.pro/
Project-URL: Documentation, https://github.com/NSb0y/loggerbot
Project-URL: Repository, https://github.com/NSb0y/loggerbot
Project-URL: Bug Tracker, https://github.com/NSb0y/loggerbot/issues
Keywords: telegram,logging,bot,rate-limiting,message-queuing
Classifier: Development Status :: 3 - Alpha
Classifier: Intended Audience :: Developers
Classifier: License :: OSI Approved :: MIT License
Classifier: Operating System :: OS Independent
Classifier: Programming Language :: Python :: 3
Classifier: Programming Language :: Python :: 3.6
Classifier: Programming Language :: Python :: 3.7
Classifier: Programming Language :: Python :: 3.8
Classifier: Programming Language :: Python :: 3.9
Classifier: Programming Language :: Python :: 3.10
Classifier: Programming Language :: Python :: 3.11
Requires-Python: >=3.6
License-File: LICENSE
Requires-Dist: requests>=2.25.1
